mdetsyn/__init__.py
mdetsyn/detsyn.py
mdetsyn/helpers.py
mdetsyn-0.0.4.post1.data/data/requirements.txt
mdetsyn-0.0.4.post1.dist-info/METADATA
mdetsyn-0.0.4.post1.dist-info/WHEEL
mdetsyn-0.0.4.post1.dist-info/top_level.txt
mdetsyn-0.0.4.post1.dist-info/RECORD
