Metadata-Version: 2.1
Name: mdetsyn
Version: 0.0.4.post1
Summary: Data Synthesis pipeline to generate object detection data
Author: PD-Mera
Author-email: phuongdong1772000@gmail.com
Requires-Dist: opencv-python
Requires-Dist: pillow
